{
  "claim_ceiling_status": "PRESERVED",
  "fixed512_failure_count": 18,
  "schema_id": "kt.g32s.fixed512_failure_by_stratum.v1",
  "status": "PASS_STRATIFIED_FAILURES_BOUND",
  "strata": {
    "HIGH_PROXY_COMPLEXITY": {
      "fixed512_failures": 6,
      "no_correct_arm_rows": 5,
      "rows": 19
    },
    "LOW_PROXY_COMPLEXITY": {
      "fixed512_failures": 5,
      "no_correct_arm_rows": 5,
      "rows": 38
    },
    "MEDIUM_PROXY_COMPLEXITY": {
      "fixed512_failures": 7,
      "no_correct_arm_rows": 4,
      "rows": 43
    }
  },
  "training_authority": false,
  "unknown_failure_rate": 0.7777777777777778
}
