{
  "claim_ceiling_status": "UNCHANGED",
  "created_utc": "2026-05-27T14:33:13Z",
  "current_head": "225dc489e70d1acaff40751dedfe539c1e3661c4",
  "gaps_closed_by_this_lane": [
    "V12 evidence import gate",
    "V12 specialist-route derivation replay",
    "canonical candidate route rule without router-superiority claim",
    "adapter isolation hardening",
    "accountability receipt binding",
    "self-deception scorecard binding",
    "no-scaffold measured-runtime gate",
    "KT-hat utility-under-constraint gate",
    "cross-domain admission engine parked as non-runtime law",
    "DCI and repo state-diff proof",
    "V13 packet-generation spec"
  ],
  "missing_surfaces": [],
  "schema_id": "kt.v13.gap_matrix.v1"
}
