{
  "adapter_training_authorized": false,
  "allowed_claims": [
    "G2 output-new-token compression anchor exists.",
    "Current full-system compression frontier remains open."
  ],
  "claim_ceiling_preserved": true,
  "commercial_claim": false,
  "external_validation_claim": false,
  "forbidden_claims": [
    "G2 full-system compression recovered.",
    "91% full-system compression restored.",
    "G2 output-token TPC equals current full-system TPC."
  ],
  "frontier_claim": false,
  "g2_recovered_claim": false,
  "learned_router_superiority_claim": false,
  "multi_lobe_superiority_claim": false,
  "policy_optimization_authorized": false,
  "production_readiness_claim": false,
  "promotion_authority": false,
  "router_superiority_claim": false,
  "router_training_authorized": false,
  "runtime_authority": false,
  "s_tier_claim": false,
  "schema_id": "kt.v17_7_4.token_accounting_claim_boundary_receipt.v1",
  "seven_b_claim": false,
  "status": "PASS",
  "v18_runtime_authority": false
}
