{
  "adapter_training_authorized": false,
  "claim_ceiling_preserved": true,
  "learned_router_superiority_claim": false,
  "options": [
    {
      "authority_gain": "LOW_FROM_TIER_2",
      "move": "TARGETED_REPLAY_DESIGN_NEXT",
      "selected": false
    },
    {
      "authority_gain": "HIGH",
      "move": "TRUE_GENERATION_MINI_FURNACE_REQUIRED",
      "selected": true
    },
    {
      "authority_gain": "MEDIUM",
      "move": "LARGER_EVIDENCE_ACQUISITION_NEXT",
      "selected": false
    },
    {
      "authority_gain": "LOW",
      "move": "SOURCE_REPLAY_DIAGNOSTIC_ONLY",
      "selected": false
    },
    {
      "authority_gain": "NONE",
      "move": "DO_NOTHING",
      "selected": false
    }
  ],
  "policy_optimization_authorized": false,
  "promotion_authority": false,
  "router_training_authorized": false,
  "runtime_authority": false,
  "schema_id": "kt.v17_7_3.next_move_cost_risk_ledger.v1",
  "status": "PASS",
  "v18_runtime_authority": false
}
