{
  "adapter_training_authorized": false,
  "claim_ceiling_preserved": true,
  "current_authority": "EXECUTION_PACKET_READY_ONLY",
  "fresh_generation_authority_earned": false,
  "learned_router_superiority_claim": false,
  "policy_optimization_authorized": false,
  "promotion_authority": false,
  "router_training_authorized": false,
  "runtime_authority": false,
  "schema_id": "kt.v17_7_4.measurement_authority_update_contract.v1",
  "status": "READY_FOR_RUNTIME_MEASUREMENT",
  "v18_runtime_authority": false
}
