{
  "claim_ceiling_preserved": true,
  "created_utc": "2026-05-31T21:51:05Z",
  "current_head": "61631ea22f4a61c16eaa1efaecc0a32a4364f9de",
  "program_id": "KT_V16_REVIEW_V17_CANARY_AND_V18_COALITION_BUILDER",
  "rows": [
    {
      "admission_state": "LAB_PREP_ONLY",
      "canary_required": true,
      "family_id": "quantitative_reasoning_candidate",
      "promotion_authority": false,
      "runtime_authority": false
    },
    {
      "admission_state": "LAB_PREP_ONLY",
      "canary_required": true,
      "family_id": "hat_salvage_candidate",
      "promotion_authority": false,
      "runtime_authority": false
    },
    {
      "admission_state": "LAB_PREP_ONLY",
      "canary_required": true,
      "family_id": "route_regret_policy_candidate",
      "promotion_authority": false,
      "runtime_authority": false
    },
    {
      "admission_state": "LAB_PREP_ONLY",
      "canary_required": true,
      "family_id": "math_act_candidate",
      "promotion_authority": false,
      "runtime_authority": false
    },
    {
      "admission_state": "LAB_PREP_ONLY",
      "canary_required": true,
      "family_id": "claim_boundary_candidate",
      "promotion_authority": false,
      "runtime_authority": false
    },
    {
      "admission_state": "LAB_PREP_ONLY",
      "canary_required": true,
      "family_id": "evidence_grounding_candidate",
      "promotion_authority": false,
      "runtime_authority": false
    },
    {
      "admission_state": "LAB_PREP_ONLY",
      "canary_required": true,
      "family_id": "contradiction_paradox_candidate",
      "promotion_authority": false,
      "runtime_authority": false
    },
    {
      "admission_state": "LAB_PREP_ONLY",
      "canary_required": true,
      "family_id": "red_assault_misdirection_candidate",
      "promotion_authority": false,
      "runtime_authority": false
    },
    {
      "admission_state": "LAB_PREP_ONLY",
      "canary_required": true,
      "family_id": "long_horizon_state_candidate",
      "promotion_authority": false,
      "runtime_authority": false
    },
    {
      "admission_state": "LAB_PREP_ONLY",
      "canary_required": true,
      "family_id": "tool_code_execution_candidate",
      "promotion_authority": false,
      "runtime_authority": false
    },
    {
      "admission_state": "LAB_PREP_ONLY",
      "canary_required": true,
      "family_id": "audit_proof_candidate",
      "promotion_authority": false,
      "runtime_authority": false
    }
  ],
  "schema_id": "kt.crossroad_admission_matrix.v1",
  "status": "PASS"
}
