{
  "claim_ceiling_status": "PRESERVED",
  "derived_field_dependency_count": 0,
  "duplicate_work_key_count": 0,
  "edge_execution_count": 36,
  "l0_correct": 261,
  "measured_record_count": 1176,
  "natural_pair_count": 300,
  "negative_savings_rows": 0,
  "official_active_statuses": [
    "BLOCK_TOKEN_ECONOMICS",
    "BLOCK_UNSAFE_STOP"
  ],
  "official_recomputed_status": "BLOCK_UNSAFE_STOP",
  "official_unlawful_reference_count": 3,
  "output_tokens_saved": 1500,
  "paired_correctness_damage": 0,
  "predicate_vector": {
    "dangling_repeated_markers": 1,
    "exact_no_intervention_fallback_count": 271,
    "l0_full_tokens_per_correct": 383.4406130268199,
    "median_physical_output_token_savings": 0.0,
    "phase_counts": {
      "edge": 36,
      "natural": 600,
      "timing": 540,
      "warmup": 9
    },
    "repaired_unsafe_stop_count": 0,
    "s1_full_tokens_per_correct": 377.69348659003833,
    "semantic_post_boundary_trailers": 15,
    "trimmed_mean_physical_output_token_savings": 0.0
  },
  "raw_prefix_mismatch_count": 0,
  "record_count_total": 1185,
  "repaired_counterfactual_status": "BLOCK_TOKEN_ECONOMICS",
  "s1_correct": 261,
  "schema_id": "kt.stop300.v41.cleanroom_recomputation.v2",
  "scorer_reconciliation_mismatch_count": 0,
  "source_assessment_sha256": "e8152d7f08b668e3ac1d0d173140872a48a0eea2849cfa45da84568725305143",
  "timing_triplet_count": 180
}
