{
  "activation_review_authorized": false,
  "authoritative_lane": "B04_R6_CANDIDATE_V2_DISQUALIFICATION_AND_CLOSEOUT_OR_MAJOR_REDESIGN",
  "current_git_head": "e689f74129940d4a24ddf5ea2fb68268e355196f",
  "forbidden_claims": [
    "r6_open",
    "learned_router_superiority_earned",
    "activation_review_authorized",
    "learned_router_activated",
    "learned_router_cutover_authorized",
    "multi_lobe_authorized",
    "package_promotion_approved",
    "commercial_broadening"
  ],
  "generated_utc": "2026-04-28T14:38:54Z",
  "learned_router_activated": false,
  "learned_router_cutover_authorized": false,
  "learned_router_superiority_earned": false,
  "multi_lobe_authorized": false,
  "next_lawful_move": "AUTHOR_B04_R6_MAJOR_ROUTER_REDESIGN_SCOPE_PACKET__NEW_ARCHITECTURE_AND_NEW_BLIND_UNIVERSE_REQUIRED",
  "options": [
    {
      "addresses": [
        "ABSTENTION_COLLAPSE",
        "OVERRouting_COLLAPSE"
      ],
      "admissible_for_next_scope_court": true,
      "candidate_generation_authorized_now": false,
      "materially_different_from_v1_v2": true,
      "option_id": "ABSTENTION_FIRST_STATIC_HOLD_ROUTER",
      "required_new_evidence": [
        "new_architecture_source_packet",
        "new_blind_universe",
        "static_hold_proof"
      ]
    },
    {
      "addresses": [
        "ABSTENTION_COLLAPSE",
        "CONTROL_DEGRADATION"
      ],
      "admissible_for_next_scope_court": true,
      "candidate_generation_authorized_now": false,
      "materially_different_from_v1_v2": true,
      "option_id": "UNCERTAINTY_GATED_CONFORMAL_ROUTER",
      "required_new_evidence": [
        "calibration_receipt",
        "coverage_threshold_contract",
        "new_blind_universe"
      ]
    },
    {
      "addresses": [
        "STATIC_COMPARATOR_DOMINANCE",
        "CONTROL_DEGRADATION"
      ],
      "admissible_for_next_scope_court": true,
      "candidate_generation_authorized_now": false,
      "materially_different_from_v1_v2": true,
      "option_id": "TWO_STAGE_PERFORMANCE_PREDICTOR_SELECTOR",
      "required_new_evidence": [
        "feature_substrate_receipt",
        "predictor_holdout_receipt",
        "new_blind_universe"
      ]
    },
    {
      "addresses": [
        "OVERRouting_COLLAPSE",
        "CONTROL_DEGRADATION"
      ],
      "admissible_for_next_scope_court": true,
      "candidate_generation_authorized_now": false,
      "materially_different_from_v1_v2": true,
      "option_id": "COST_AWARE_SELECTOR_WITH_STATIC_FALLBACK",
      "required_new_evidence": [
        "cost_contract",
        "fallback_preservation_receipt",
        "new_blind_universe"
      ]
    },
    {
      "addresses": [],
      "admissible_for_next_scope_court": false,
      "candidate_generation_authorized_now": false,
      "materially_different_from_v1_v2": false,
      "option_id": "QUICK_CANDIDATE_V3_PATCH",
      "rejection_reason": "A patch-style v3 would reuse a disqualified family and risks overfitting invalidated screen evidence.",
      "required_new_evidence": []
    }
  ],
  "package_promotion_remains_deferred": true,
  "previous_authoritative_lane": "B04_R6_SECOND_SHADOW_SCREEN_FORENSIC_AND_RERUN_BAR",
  "quick_candidate_v3_patch_allowed": false,
  "r6_authorized": false,
  "r6_open": false,
  "schema_id": "kt.operator.b04_r6_major_redesign_options_matrix.v1",
  "schema_version": "1.0.0",
  "selected_path": "MAJOR_REDESIGN_SCOPE_COURT",
  "status": "PASS",
  "subject_main_head": "e689f74129940d4a24ddf5ea2fb68268e355196f",
  "trust_zone_law_unchanged": true,
  "truth_engine_derivation_law_unchanged": true
}
