{
  "execution_status": "PASS__UNKNOWN_ZONE_AND_PRODUCT_PROOF_BOUNDARIES_REDUCED",
  "generated_utc": "2026-04-26T19:08:01Z",
  "next_lawful_move": "AUTHOR_TRUST_ZONE_BOUNDARY_PURIFICATION_CLOSEOUT_OR_NEXT_BATCH_PACKET",
  "outcome": "BUYER_SAFE_LANGUAGE_PATCH_QUEUE_BOUND",
  "package_promotion_remains_deferred": true,
  "patch_entries": [
    {
      "line": 2,
      "path": "docs/generated/kt_doctrine_compiler_spec.json",
      "required_patch": "replace frontier-ceiling shorthand with bounded canonical claim-boundary language before buyer-facing promotion",
      "terms": [
        "frontier"
      ]
    },
    {
      "line": 9,
      "path": "docs/generated/kt_doctrine_ratification_log.json",
      "required_patch": "replace frontier-ceiling shorthand with bounded canonical claim-boundary language before buyer-facing promotion",
      "terms": [
        "frontier"
      ]
    },
    {
      "line": 6,
      "path": "docs/generated/kt_master_spec.md",
      "required_patch": "replace frontier-ceiling shorthand with bounded canonical claim-boundary language before buyer-facing promotion",
      "terms": [
        "frontier"
      ]
    },
    {
      "line": 3,
      "path": "docs/generated/profiles/kt_outsider_onboarding_profile.json",
      "required_patch": "replace frontier-ceiling shorthand with bounded canonical claim-boundary language before buyer-facing promotion",
      "terms": [
        "frontier"
      ]
    }
  ],
  "patch_required_count": 4,
  "safe_language": "KT has governed, receipt-backed, fail-closed execution in the validated local_verifier_mode wedge.",
  "schema_id": "kt.operator.buyer_safe_language_patch_queue.v1",
  "status": "PASS",
  "truth_engine_derivation_law_unchanged": true
}
