{
  "baseline_verdict_path": "KT_PROD_CLEANROOM/reports/cohort0_post_f_track_02_frozen_baseline_audit_packet.json",
  "crosswalk": {
    "authority_state": {
      "at_current_truth": "MINIMUM_PATH_COMPLETE_THROUGH_GATE_F__BROAD_REAUDIT_PASS__TRACK_01_CLOSED__TRACK_02_SHARED_HARVEST_COMPLETE",
      "at_frozen_baseline": "MINIMUM_PATH_COMPLETE_THROUGH_GATE_F__BROAD_REAUDIT_PASS__EXPANSION_AUTHORIZED",
      "delta": "Current truth adds Track 01 bounded comparative proof closure and a clean Track 02 authority-partitioned audit footing.",
      "what_improved": "Track 01 is closed and Track 02 is now executing from a tracked clean harvest path.",
      "what_stayed_weak": "H1, externality ceiling, platform enforcement, canonical merge, and commercial proof all remain open."
    },
    "benchmark_readiness": {
      "at_current_truth": "BOUNDARY_FAIR_INTERNAL_BENCHMARK_CLOSED__TRACK_01_ONLY",
      "at_frozen_baseline": "SCOPE_DEFINED_ONLY__NOT_EXECUTED",
      "delta": "Track 01 closes the first bounded benchmark lane.",
      "what_is_newly_benchmark_ready": "Internal bounded governed-execution comparison on the local_verifier_mode wedge.",
      "what_is_still_not_benchmark_ready": "Public leaderboards, enterprise bakeoffs, cross-host capability comparisons, Kaggle or math tracks."
    },
    "claim_safety": {
      "at_current_truth": "EXCELLENT__MAINTAINED_THROUGH_TRACK_01_AND_TRACK_02",
      "at_frozen_baseline": "EXCELLENT__BOUNDARIES_EXPLICIT",
      "delta": "Track 01 and Track 02 both preserved forbidden-interpretation discipline.",
      "what_improved": "Evidence separation is now even tighter.",
      "what_stayed_weak": "No weakness on this axis beyond human retelling risk."
    },
    "commercial_product_truth": {
      "at_current_truth": "SAME__NO_COMMERCIAL_PROMOTION",
      "at_frozen_baseline": "PRE_REVENUE__SINGLE_TENANT_BOUNDED_VERIFIER",
      "delta": "No commercial plane improvement occurred.",
      "what_improved": "Nothing on this axis.",
      "what_stayed_weak": "Zero customers, zero revenue, single-tenant only."
    },
    "control_plane_truth": {
      "at_current_truth": "SAME__PLUS_CONTROLLED_POST_F_TRACKS_EXECUTING",
      "at_frozen_baseline": "MINIMUM_PATH_COMPLETE__PREDICATE_CHAIN_SATISFIED",
      "delta": "No sovereign gate changed; only the post-F track layer advanced.",
      "what_improved": "Controlled expansion is behaving constitutionally.",
      "what_stayed_weak": "H1 remains blocked."
    },
    "full_system_execution_readiness": {
      "at_current_truth": "SAME__BROADER_RATIFICATION_BLOCKED",
      "at_frozen_baseline": "BOUNDED_MINIMUM_PATH_COMPLETE__BROADER_RATIFICATION_BLOCKED",
      "delta": "No full-system readiness change occurred.",
      "what_improved": "Nothing on this axis.",
      "what_stayed_weak": "No civilization-grade ratification, no H1, no E2+."
    },
    "governed_system": {
      "at_current_truth": "Same plus Track 01 bounded proof frozen and Track 02 dual audit running",
      "at_frozen_baseline": "Gate D cleared, Gate E open, Gate F narrow wedge confirmed, re-audit passed",
      "delta": "Track 01 adds a real bounded proof layer; Track 02 adds an adversarial audit lane.",
      "what_improved": "Governed proof and review surfaces expanded without widening product truth.",
      "what_stayed_weak": "No external independent ratification."
    },
    "historical_bounded_proof": {
      "at_current_truth": "TRACK_01_TWO_WAVE_ADVANTAGE_CONFIRMED__LOCAL_VERIFIER_MODE_ONLY",
      "at_frozen_baseline": "NO_TRACK_01_COMPARATIVE_EXECUTION_ADMITTED",
      "delta": "The largest substantive improvement is the addition of a repeated bounded comparative proof packet.",
      "what_improved": "Track 01 is now real and frozen.",
      "what_stayed_weak": "Comparator set remains tiny and category-bounded."
    },
    "open_blockers": {
      "at_current_truth": [
        "The same five blocker families remain open"
      ],
      "at_frozen_baseline": [
        "H1 activation closed",
        "External capability unconfirmed",
        "Externality ceiling at E1",
        "Platform enforcement unproven",
        "No external customer or revenue"
      ],
      "delta": "No structural blocker was cleared by Track 01 or Track 02 execution.",
      "what_stayed_weak": "All five blocker families remain active."
    },
    "post_f_maturity_classification": {
      "surfaces_promoted_at_current_truth_vs_baseline": [
        {
          "baseline_classification": "intended_but_not_lawfully_promoted",
          "current_truth_classification": "canonical_but_bounded",
          "promotion_event": "Track 01 final summary packet",
          "surface": "Track 01 bounded comparative proof"
        }
      ],
      "surfaces_unchanged": [
        "Successor control plane remains canonical_and_ratified",
        "Gate F wedge remains canonical_but_bounded",
        "H1 activation remains intended_but_not_lawfully_promoted",
        "Commercial validation remains intended_but_not_lawfully_promoted"
      ]
    },
    "repo_architecture": {
      "at_current_truth": "Same spine plus Track 01 execution artifacts and Track 02 tracked courts",
      "at_frozen_baseline": "Clean canonical spine through Gate F with quarantine law and protected merge discipline",
      "delta": "Post-F expansion logic is now executing through bounded comparative and audit courts.",
      "what_improved": "Comparative proof and dual-audit machinery are now both present.",
      "what_stayed_weak": "No external code audit and repo-root import fragility remain."
    },
    "runtime_capability_truth": {
      "at_current_truth": "SAME__NO_RUNTIME_CAPABILITY_PROMOTION",
      "at_frozen_baseline": "LOCAL_VERIFIER_MODE_WEDGE_ONLY__E1",
      "delta": "No runtime promotion occurred between baseline and current truth.",
      "what_improved": "Nothing on runtime breadth.",
      "what_stayed_weak": "E1 ceiling, no H1, no E2+."
    }
  },
  "current_truth_commit": "bb49da82d50ede03f04d165ed883cf05df0c156e",
  "current_truth_verdict_path": "KT_PROD_CLEANROOM/reports/cohort0_post_f_track_02_current_truth_audit_packet.json",
  "execution_status": "PASS__DELTA_CROSSWALK_COMPLETE",
  "frozen_baseline_commit": "558c9a46e87dbe9fed1884a4d24305ed2450929d",
  "generated_utc": "2026-04-24T06:35:11Z",
  "preserve_separate_verdicts": true,
  "required_questions": {
    "what_improved_because_system_improved": "Track 01 closed as a repeated bounded comparative proof, and Track 02 now has a clean shared-harvest audit footing.",
    "what_is_newly_benchmark_ready": "The internal bounded comparator lane for the confirmed local_verifier_mode wedge.",
    "what_is_still_not_lawfully_claimable": "Best-AI, broad reasoning superiority, full-system superiority, enterprise readiness, cross-host capability, Kaggle carryover, and multi-tenant claims.",
    "what_remains_civilization_ratification_limited": "Anything beyond E1 and beyond bounded verifier-mode proof remains blocked.",
    "what_remains_doctrine_or_lab_only": "Broader lobe, router, Kaggle, H1, and civilization-scale claims.",
    "what_remains_product_limited": "Gate F remains one narrow local_verifier_mode wedge only.",
    "what_stayed_weak": "Runtime breadth, H1, E2+, platform enforcement, and commercial validation all stayed weak."
  },
  "schema_id": "kt.operator.cohort0_post_f_track_02_dual_audit_delta_crosswalk.v1",
  "status": "PASS",
  "work_order_id": "cohort0_post_f_track_02_dual_audit_work_order"
}
