{
  "advisor_outputs_own_pass_fail_authority": false,
  "artifact_id": "KT_13_LOBE_TRANCHE_READINESS_INSPECTION_RECEIPT",
  "beyond_sota_claim_authorized": false,
  "blocker_count": 0,
  "blockers": [],
  "branch_bound_training_allowed": false,
  "canonical_lobe_count": 13,
  "canonical_lobes": [
    "strategic_synthesis_lobe",
    "audit_reasoning_lobe",
    "formal_proof_reasoning_lobe",
    "contradiction_paradox_lobe",
    "temporal_chronology_lobe",
    "cross_domain_patterncraft_lobe",
    "grounded_evidence_lobe",
    "regulated_domain_lobe",
    "commercial_operator_lobe",
    "execution_tool_lobe",
    "context_memory_compression_lobe",
    "learning_delta_lobe",
    "adversarial_red_assault_lobe"
  ],
  "category_leadership_claim_authorized": false,
  "claim_ceiling_unchanged": true,
  "code_owned_gates_retain_pass_fail_authority": true,
  "commercial_claim_authorized": false,
  "current_head": "88d45275e5553fcaefcf89bfa47ce30637f975c6",
  "external_audit_accepted": false,
  "external_audit_complete": false,
  "forbidden_training_targets": [
    "claim_boundary",
    "proof_validator",
    "truth_engine",
    "bio_med_firewall",
    "evaluator_integrity",
    "primitive_invariance",
    "metacognitive_admission",
    "runtime_execution_chain",
    "delta_to_primitive",
    "router_control",
    "router_controller",
    "adapter_forge",
    "lobe_trainer",
    "benchmark_evaluator",
    "external_attestation",
    "commercial_boundary",
    "truth_grounding",
    "claim_compiler",
    "detached_verifier",
    "supply_chain_gate"
  ],
  "frontier_parity_claim_authorized": false,
  "full_adaptive_orchestration_production_ready": false,
  "future_kaggle_training_restricted_to_13_lobe_ids": true,
  "generated_utc": "2026-05-23T21:35:31Z",
  "historical_lobe_labels_preserved_as_compat_records": true,
  "kimi_parity_claim_authorized": false,
  "multi_lobe_superiority_claim_authorized": false,
  "next_lawful_move": "RUN_13_LOBE_7B_TRANCHE",
  "outcome": "KT_13_LOBE_TRANCHE_READY__RUN_13_LOBE_7B_TRANCHE_NEXT__CLAIM_CEILING_PRESERVED",
  "program_id": "VERIFY_KT_13_LOBE_TRANCHE_READINESS",
  "required_kaggle_outputs": [
    "head_binding_receipt.json",
    "run_manifest.json",
    "training_receipt.json",
    "eval_receipt.json",
    "negative_result_ledger.json",
    "router_trace.csv",
    "router_trace.json",
    "router_vs_static_scorecard.json",
    "router_vs_best_adapter_scorecard.json",
    "safetensors_hash_manifest.json",
    "kt_hat_adapter_mount_manifest.json",
    "benchmark_tranche_receipt.json",
    "blocker_ledger.json",
    "KT_13_LOBE_ASSESSMENT_REVIEW_SUMMARY.json",
    "assessment_summary.json",
    "cuda_environment_receipt.json",
    "qlora_effectiveness_receipt.json",
    "hf_cache_network_retry_receipt.json",
    "partial_run_resume_receipt.json"
  ],
  "router_proof_order_preserved": [
    "static_baseline",
    "shadow_evaluation",
    "best_static_comparison",
    "learned_router_candidate",
    "statistical_evidence",
    "multi_lobe_orchestration"
  ],
  "router_superiority_claim_authorized": false,
  "s_tier_claim_authorized": false,
  "schema_id": "kt.13_lobe_tranche.readiness_inspection_receipt.v1",
  "seven_b_amplification_proven": false,
  "trust_zone_law_changed": false,
  "truth_engine_law_changed": false
}
