{
  "schema_id": "kt.unified_convergence.lineage_reconstruction.v1",
  "work_order_id": "KT_UNIFIED_CONVERGENCE_MAX_POWER_CAMPAIGN_V2_1_1_FINAL",
  "generated_utc": "2026-03-20T12:53:01.9928144-05:00",
  "current_git_head": "494cd490a6512b9bfa937c82886db625143d38ae",
  "layers": [
    {
      "layer_id": "A_HISTORICAL_HARDENING_PUBLIC_DEFENSIBILITY",
      "status": "historically_proven",
      "summary": "Historical bounded frontier target remains strong and bounded, but historical only."
    },
    {
      "layer_id": "B_CURRENT_SOVEREIGN_CONTROL_PLANE",
      "status": "current_head_proven",
      "summary": "Child campaign F01-F09 passed with bounded current-head trust, verifier, release, product wedge, and company diligence outputs."
    },
    {
      "layer_id": "C_RUNTIME_CIVILIZATION_CAPABILITY_PLANE",
      "status": "current_head_partially_proven",
      "summary": "Runtime truth exists but is uneven. No full civilization run is proven. Adapter layer remains stubbed and openclaw remains doctrinal-only."
    },
    {
      "layer_id": "D_PRODUCT_AND_COMMERCIAL_PLANE",
      "status": "current_head_partially_proven",
      "summary": "A bounded noncommercial evaluation wedge is active. Commercial and enterprise-wide truth remain bounded downward."
    }
  ],
  "recurring_success_patterns": [
    "bounded upgrades without laundering adjacent truths",
    "child-only supersession instead of parent mutation",
    "anti-theater retention instead of fake promotion"
  ],
  "recurring_failure_patterns": [
    "governance outpaces runtime realization",
    "tooling and runtime blur together through compatibility leakage",
    "repo-root and package-root parity remains unresolved",
    "adapter civilization rhetoric outruns adapter registry reality"
  ]
}
