{
  "authoritative_single_axis_transfer_candidate_report_ref": "D:/user/rober/OneDrive/Kings_Theorem_Active/tmp/cohort0_single_axis_transfer_candidate_live/single_axis_transfer_candidate_report.json",
  "blocked_family_ids": [
    "CHILD_ANOMALY_PRESERVATION"
  ],
  "carrier_surface_role": "TRACKED_CARRIER_ONLY_SINGLE_AXIS_TRANSFER_CANDIDATE_REPORT",
  "claim_boundary": "This report digests single-axis outcomes into hard lab-only transfer decisions. It does not reopen the counted lane.",
  "controls_preserved": true,
  "current_git_head": "66eb05ea5b321be86a1e320cde5fd667a06038e9",
  "generated_utc": "2026-04-12T21:23:33Z",
  "rows": [
    {
      "alpha_liability_exposed_count": 15,
      "anti_alpha_liability_clarity": "STRENGTHENED",
      "control_family": false,
      "counts_as_counted_progress_now": false,
      "disposition": "PROMOTE_TO_PAIRWISE_LAB_ESCALATION",
      "family_id": "P2_SIGNAL_NOISE_SEPARATION",
      "next_lab_action": "AUTHOR_PAIRWISE_CRUCIBLE_INPUTS",
      "route_delta_count": 14,
      "sharpened_on_intended_axis": true,
      "target_lobe_id": "lobe.p2.v1",
      "transfer_candidate_status": "TRANSFER_CANDIDATE_ADMISSIBLE_FOR_COUNTED_LANE",
      "wedge_sharpening_count": 9
    },
    {
      "alpha_liability_exposed_count": 7,
      "anti_alpha_liability_clarity": "STILL_WEAK",
      "control_family": false,
      "counts_as_counted_progress_now": false,
      "disposition": "KEEP_LAB_ONLY_REVISE_SINGLE_AXIS",
      "family_id": "CHILD_ANOMALY_PRESERVATION",
      "next_lab_action": "REVISE_SINGLE_AXIS_WEDGE_OR_INTENSITY",
      "route_delta_count": 7,
      "sharpened_on_intended_axis": false,
      "target_lobe_id": "lobe.child.v1",
      "transfer_candidate_status": "ANTI_ALPHA_LIABILITY_EXPOSED_BUT_ROUTE_HYPOTHESIS_STILL_WEAK",
      "wedge_sharpening_count": 2
    },
    {
      "alpha_liability_exposed_count": 16,
      "anti_alpha_liability_clarity": "STRENGTHENED",
      "control_family": false,
      "counts_as_counted_progress_now": false,
      "disposition": "PROMOTE_TO_PAIRWISE_LAB_ESCALATION",
      "family_id": "STRATEGIST_CONSEQUENCE_CHAIN",
      "next_lab_action": "AUTHOR_PAIRWISE_CRUCIBLE_INPUTS",
      "route_delta_count": 15,
      "sharpened_on_intended_axis": true,
      "target_lobe_id": "lobe.strategist.v1",
      "transfer_candidate_status": "TRANSFER_CANDIDATE_ADMISSIBLE_FOR_COUNTED_LANE",
      "wedge_sharpening_count": 11
    },
    {
      "alpha_liability_exposed_count": 14,
      "anti_alpha_liability_clarity": "STRENGTHENED",
      "control_family": false,
      "counts_as_counted_progress_now": false,
      "disposition": "PROMOTE_TO_PAIRWISE_LAB_ESCALATION",
      "family_id": "SCOUT_SPARSE_SEARCH",
      "next_lab_action": "AUTHOR_PAIRWISE_CRUCIBLE_INPUTS",
      "route_delta_count": 13,
      "sharpened_on_intended_axis": true,
      "target_lobe_id": "lobe.scout.v1",
      "transfer_candidate_status": "TRANSFER_CANDIDATE_ADMISSIBLE_FOR_COUNTED_LANE",
      "wedge_sharpening_count": 9
    },
    {
      "alpha_liability_exposed_count": 12,
      "anti_alpha_liability_clarity": "STRENGTHENED",
      "control_family": false,
      "counts_as_counted_progress_now": false,
      "disposition": "PROMOTE_TO_PAIRWISE_LAB_ESCALATION",
      "family_id": "AUDITOR_ADMISSIBILITY_FAIL_CLOSED",
      "next_lab_action": "AUTHOR_PAIRWISE_CRUCIBLE_INPUTS",
      "route_delta_count": 11,
      "sharpened_on_intended_axis": true,
      "target_lobe_id": "lobe.auditor.v1",
      "transfer_candidate_status": "TRANSFER_CANDIDATE_ADMISSIBLE_FOR_COUNTED_LANE",
      "wedge_sharpening_count": 7
    },
    {
      "alpha_liability_exposed_count": 11,
      "anti_alpha_liability_clarity": "STRENGTHENED",
      "control_family": false,
      "counts_as_counted_progress_now": false,
      "disposition": "PROMOTE_TO_PAIRWISE_LAB_ESCALATION",
      "family_id": "BETA_SECOND_ORDER_REFRAME",
      "next_lab_action": "AUTHOR_PAIRWISE_CRUCIBLE_INPUTS",
      "route_delta_count": 10,
      "sharpened_on_intended_axis": true,
      "target_lobe_id": "lobe.beta.v1",
      "transfer_candidate_status": "TRANSFER_CANDIDATE_ADMISSIBLE_FOR_COUNTED_LANE",
      "wedge_sharpening_count": 6
    },
    {
      "alpha_liability_exposed_count": 16,
      "anti_alpha_liability_clarity": "CONTROL_ONLY",
      "control_family": true,
      "counts_as_counted_progress_now": false,
      "disposition": "PRESERVE_CONTROL",
      "family_id": "BOUNDARY_ABSTENTION_CONTROL",
      "next_lab_action": "PRESERVE_AS_CONTROL",
      "route_delta_count": 16,
      "sharpened_on_intended_axis": false,
      "target_lobe_id": "",
      "transfer_candidate_status": "CONTROL_ONLY_NOT_TRANSFER_CANDIDATE",
      "wedge_sharpening_count": 0
    },
    {
      "alpha_liability_exposed_count": 0,
      "anti_alpha_liability_clarity": "CONTROL_ONLY",
      "control_family": true,
      "counts_as_counted_progress_now": false,
      "disposition": "PRESERVE_CONTROL",
      "family_id": "STATIC_NO_ROUTE_CONTROL",
      "next_lab_action": "PRESERVE_AS_CONTROL",
      "route_delta_count": 0,
      "sharpened_on_intended_axis": false,
      "target_lobe_id": "lobe.alpha.v1",
      "transfer_candidate_status": "CONTROL_ONLY_NOT_TRANSFER_CANDIDATE",
      "wedge_sharpening_count": 0
    }
  ],
  "schema_id": "kt.operator.single_axis_transfer_candidate_report.v1",
  "status": "PASS",
  "subject_head": "5f1fb07200fe8fcbce57ef1ed92d1189ab571c91",
  "survivor_family_ids": [
    "P2_SIGNAL_NOISE_SEPARATION",
    "STRATEGIST_CONSEQUENCE_CHAIN",
    "SCOUT_SPARSE_SEARCH",
    "AUDITOR_ADMISSIBILITY_FAIL_CLOSED",
    "BETA_SECOND_ORDER_REFRAME"
  ]
}
