{
  "$id": "https://kt.local/schemas/kt.v17_7_4.answer_surface_failure_review.schema.json",
  "$schema": "https://json-schema.org/draft/2020-12/schema",
  "additionalProperties": true,
  "properties": {
    "claim_ceiling_preserved": {
      "const": true
    },
    "runtime_authority": {
      "const": false
    },
    "schema_id": {
      "type": "string"
    }
  },
  "required": [
    "schema_id",
    "claim_ceiling_preserved"
  ],
  "title": "KT V17.7.4 Answer Surface Failure Review",
  "type": "object"
}
