{
  "allowed_repairs": [
    "specialist math routing under verifier/finalizer gate",
    "adapter isolation probe",
    "failure confession and success admissibility receipts",
    "KTG3FULL V1.2 measurement packet"
  ],
  "claim_ceiling_preserved": true,
  "forbidden_repairs": [
    "global adapter promotion",
    "broad retraining",
    "commercial or frontier claim",
    "niche result described globally"
  ],
  "promotion_eligible": false,
  "run_id": "ktak_9bede81ee8d9",
  "schema_id": "kt.repair_consequence_receipt.v1"
}
