{
  "observed_ignored_roots": {
    ".venv": {
      "exists": true,
      "files": 887,
      "dirs": 134
    },
    ".pytest_cache": {
      "exists": true,
      "files": 5,
      "dirs": 2
    },
    "__pycache__": {
      "exists": true,
      "files": 1,
      "dirs": 0
    },
    "KT_PROD_CLEANROOM/exports": {
      "exists": true,
      "files": 66982,
      "dirs": 22733
    },
    "exports": {
      "exists": true,
      "files": 28,
      "dirs": 23
    }
  },
  "secret_like_paths": [
    ".env.secret"
  ],
  "residue_present": true
}
